slackclip.py
slackclip-1.0.1.dist-info/METADATA
slackclip-1.0.1.dist-info/WHEEL
slackclip-1.0.1.dist-info/entry_points.txt
slackclip-1.0.1.dist-info/licenses/LICENSE
slackclip-1.0.1.dist-info/RECORD
