Metadata-Version: 2.4
Name: slackclip
Version: 1.0.1
Summary: Copy the contents of a Slack thread.
Project-URL: Repository, https://github.com/zachvictor/slackclip
Author: Zach Victor
Author-email: Heath Raftery <heath@empirical.ee>
License-Expression: GPL-3.0-only
License-File: LICENSE
Classifier: Development Status :: 5 - Production/Stable
Classifier: Environment :: Console
Classifier: Intended Audience :: Developers
Classifier: Topic :: Utilities
Requires-Python: >=3.10
Requires-Dist: emoji>=2.15
Requires-Dist: pyperclip>=1.11
Requires-Dist: requests>=2.32.5
Provides-Extra: dev
Requires-Dist: ruff>=0.8; extra == 'dev'
